{
  "$schema": "../../../../schema/driver.schema.json",
  "type": "cone",
  "brand": "Faital PRO",
  "model": "10PR310",
  "sizeInch": 10,
  "impedanceOhm": 16,
  "fsHz": 65,
  "qts": 0.47,
  "qes": 0.52,
  "qms": 5.3,
  "vasL": 29,
  "sdCm2": 348,
  "xmaxMm": 4.92,
  "reOhm": 12.1,
  "mmsG": 35,
  "peW": 300,
  "sensitivityDb": 97,
  "magnetMaterial": "ferrite ring",
  "weightKg": 4.1,
  "datasheetUrl": "https://faitalpro.com/en/products/LF_Loudspeakers/product_details/index.php?id=101040132"
}
